indico_payment_manual/__init__.py
indico_payment_manual/placeholders.py
indico_payment_manual/plugin.py
indico_payment_manual/static/images/logo.png
indico_payment_manual/templates/event_payment_form.html
indico_payment_manual/translations/messages.pot
indico_payment_manual/translations/cs_CZ/LC_MESSAGES/messages.mo
indico_payment_manual/translations/cs_CZ/LC_MESSAGES/messages.po
indico_payment_manual/translations/de_DE/LC_MESSAGES/messages.mo
indico_payment_manual/translations/de_DE/LC_MESSAGES/messages.po
indico_payment_manual/translations/en_CA/LC_MESSAGES/messages.mo
indico_payment_manual/translations/en_CA/LC_MESSAGES/messages.po
indico_payment_manual/translations/en_GB/LC_MESSAGES/messages.mo
indico_payment_manual/translations/en_GB/LC_MESSAGES/messages.po
indico_payment_manual/translations/es_ES/LC_MESSAGES/messages.mo
indico_payment_manual/translations/es_ES/LC_MESSAGES/messages.po
indico_payment_manual/translations/fr_FR/LC_MESSAGES/messages-js.po
indico_payment_manual/translations/fr_FR/LC_MESSAGES/messages.mo
indico_payment_manual/translations/fr_FR/LC_MESSAGES/messages.po
indico_payment_manual/translations/hu_HU/LC_MESSAGES/messages.mo
indico_payment_manual/translations/hu_HU/LC_MESSAGES/messages.po
indico_payment_manual/translations/it_IT/LC_MESSAGES/messages.mo
indico_payment_manual/translations/it_IT/LC_MESSAGES/messages.po
indico_payment_manual/translations/ja_JP/LC_MESSAGES/messages.mo
indico_payment_manual/translations/ja_JP/LC_MESSAGES/messages.po
indico_payment_manual/translations/mn_MN/LC_MESSAGES/messages.mo
indico_payment_manual/translations/mn_MN/LC_MESSAGES/messages.po
indico_payment_manual/translations/pl_PL/LC_MESSAGES/messages.mo
indico_payment_manual/translations/pl_PL/LC_MESSAGES/messages.po
indico_payment_manual/translations/pt_BR/LC_MESSAGES/messages.mo
indico_payment_manual/translations/pt_BR/LC_MESSAGES/messages.po
indico_payment_manual/translations/sv_SE/LC_MESSAGES/messages.mo
indico_plugin_payment_manual-3.3.2.dist-info/METADATA
indico_plugin_payment_manual-3.3.2.dist-info/WHEEL
indico_plugin_payment_manual-3.3.2.dist-info/entry_points.txt
indico_plugin_payment_manual-3.3.2.dist-info/RECORD
